lostproxy
