Metadata-Version: 2.1
Name: lostproxy
Version: 0.1.3
Summary: A multifunctional python proxy
Author: Joseph
Author-email: josephdove@proton.me
Classifier: Programming Language :: Python :: 3.10
Classifier: License :: OSI Approved :: MIT License
Classifier: Operating System :: OS Independent
Requires-Python: >=3.6
